gh_org_mgr/__init__.py
gh_org_mgr/_config.py
gh_org_mgr/_gh_api.py
gh_org_mgr/_gh_org.py
gh_org_mgr/_helpers.py
gh_org_mgr/_setup_team.py
gh_org_mgr/_stats.py
gh_org_mgr/manage.py
github_org_manager-0.7.5.dist-info/METADATA
github_org_manager-0.7.5.dist-info/WHEEL
github_org_manager-0.7.5.dist-info/entry_points.txt
github_org_manager-0.7.5.dist-info/licenses/LICENSE.txt
github_org_manager-0.7.5.dist-info/licenses/LICENSES/Apache-2.0.txt
github_org_manager-0.7.5.dist-info/licenses/LICENSES/CC-BY-4.0.txt
github_org_manager-0.7.5.dist-info/licenses/LICENSES/CC0-1.0.txt
github_org_manager-0.7.5.dist-info/licenses/LICENSES/MIT.txt
github_org_manager-0.7.5.dist-info/RECORD
